seadiver/__init__.py
seadiver/model.py
seadiver-0.3.6.dist-info/LICENSE
seadiver-0.3.6.dist-info/METADATA
seadiver-0.3.6.dist-info/WHEEL
seadiver-0.3.6.dist-info/top_level.txt
seadiver-0.3.6.dist-info/RECORD
