Metadata-Version: 2.1
Name: seadiver
Version: 0.3.6
Summary: A DeepLearning Framework
Home-page: https://github.com/kjchung495/seadiver
Author: KJ Chung
Author-email: kjchung495@yonsei.ac.kr
License: Apache Software License 2.0
Keywords: ANN,Artifictial Neural Network,DeepLearning
Platform: UNKNOWN
Classifier: Intended Audience :: Science/Research
Classifier: Topic :: Scientific/Engineering :: Artificial Intelligence
Classifier: License :: OSI Approved :: Apache Software License
Classifier: Operating System :: Microsoft :: Windows :: Windows 10
Classifier: Programming Language :: Python :: 3
Requires-Dist: numpy
Requires-Dist: matplotlib
